urledit
