Metadata-Version: 1.1
Name: urledit
Version: 1.1.0
Summary: Url parsing and editing as an object or in a functional style.
Home-page: https://github.com/imbolc/urledit
Author: Imbolc
Author-email: imbolc@imbolc.name
License: ISC
Platform: UNKNOWN
Classifier: Development Status :: 4 - Beta
Classifier: Intended Audience :: Developers
Classifier: License :: OSI Approved :: ISC License (ISCL)
Classifier: Programming Language :: Python
Classifier: Programming Language :: Python :: 3
